crudites/__init__.py
crudites/cli.py
crudites/globals.py
crudites/py.typed
crudites/integrations/__init__.py
crudites/integrations/auth0.py
crudites/integrations/logging.py
crudites/integrations/sentry.py
crudites/integrations/fastapi/__init__.py
crudites/integrations/fastapi/config.py
crudites/integrations/sqlalchemy/__init__.py
crudites/integrations/sqlalchemy/base.py
crudites/integrations/sqlalchemy/config.py
crudites/integrations/sqlalchemy/mixins.py
crudites-0.0.5.dist-info/METADATA
crudites-0.0.5.dist-info/WHEEL
crudites-0.0.5.dist-info/licenses/LICENSE
crudites-0.0.5.dist-info/RECORD
