Metadata-Version: 2.4
Name: crudites
Version: 0.0.5
Summary: A modern Python package for building robust web applications with FastAPI and SQLAlchemy. It focuses on providing the missing glue required to build standard CRUD applications with an opinionated view on best practices.
Project-URL: Homepage, https://github.com/jtbeach/crudites
Project-URL: Documentation, https://github.com/jtbeach/crudites#readme
Project-URL: Repository, https://github.com/jtbeach/crudites.git
Project-URL: Issues, https://github.com/jtbeach/crudites/issues
Author-email: Joel Beach <12853460+jtbeach@users.noreply.github.com>
License: MIT
License-File: LICENSE
Keywords: api,async,crud,fastapi,sqlalchemy,web
Classifier: Development Status :: 4 - Beta
Classifier: Framework :: FastAPI
Classifier: Intended Audience :: Developers
Classifier: License :: OSI Approved :: MIT License
Classifier: Programming Language :: Python :: 3
Classifier: Programming Language :: Python :: 3.12
Classifier: Topic :: Software Development :: Libraries :: Application Frameworks
Classifier: Topic :: Software Development :: Libraries :: Python Modules
Classifier: Typing :: Typed
Requires-Python: >=3.12
Requires-Dist: click>=8.1.8
Requires-Dist: json-log-formatter>=1.1.1
Requires-Dist: pydantic-settings>=2.9.1
Requires-Dist: pydantic>=2.11.5
Requires-Dist: pyjwt[crypto]>=2.10.1
Requires-Dist: sentry-sdk[fastapi,httpx]>=2.29.1
Requires-Dist: sqlalchemy[asyncio,postgresql-psycopg]>=2.0.41
